cornutils/__init__.py
cornutils/praktika.py
cornutils/test.ipynb
cornutils/test.png
cornutils-0.4.1.dist-info/WHEEL
cornutils-0.4.1.dist-info/METADATA
cornutils-0.4.1.dist-info/RECORD
