Metadata-Version: 2.1
Name: cornutils
Version: 0.4.1
Summary: Utility functions
Home-page: https://github.com/Cornelicorn/cornutils
Author: Cornelius Hoffmann
Author-email: coding@hoffmn.de
Requires-Python: >=3.7,<4.0
Classifier: Programming Language :: Python :: 3
Classifier: Programming Language :: Python :: 3.7
Classifier: Programming Language :: Python :: 3.8
Classifier: Programming Language :: Python :: 3.9
Requires-Dist: matplotlib (>=3,<4)
Requires-Dist: numpy (>=1,<2)
Requires-Dist: scipy (>=1,<2)
Project-URL: Repository, https://github.com/Cornelicorn/cornutils
